chime_frb_api/__init__.py
chime_frb_api/backends/__init__.py
chime_frb_api/backends/bucket.py
chime_frb_api/backends/distributor.py
chime_frb_api/backends/frb_master.py
chime_frb_api/core/__init__.py
chime_frb_api/core/core.py
chime_frb_api/core/exceptions.py
chime_frb_api/core/json_type.py
chime_frb_api/modules/__init__.py
chime_frb_api/modules/bucket.py
chime_frb_api/modules/buckets.py
chime_frb_api/modules/calibration.py
chime_frb_api/modules/candidates.py
chime_frb_api/modules/catalog.py
chime_frb_api/modules/distributor.py
chime_frb_api/modules/events.py
chime_frb_api/modules/metrics.py
chime_frb_api/modules/mimic.py
chime_frb_api/modules/parameters.py
chime_frb_api/modules/results.py
chime_frb_api/modules/sources.py
chime_frb_api/modules/swarm.py
chime_frb_api/modules/tns.py
chime_frb_api/modules/voe.py
chime_frb_api/modules/voe_subscribers.py
chime_frb_api/stations/__init__.py
chime_frb_api/stations/aro.py
chime_frb_api/stations/drao.py
chime_frb_api/stations/gbo.py
chime_frb_api/tests/docker-compose.yml
chime_frb_api/tests/test_audit_daemon.py
chime_frb_api/tests/test_bucket.py
chime_frb_api/tests/test_buckets.py
chime_frb_api/tests/test_calibration.py
chime_frb_api/tests/test_candidates.py
chime_frb_api/tests/test_catalog.py
chime_frb_api/tests/test_core.py
chime_frb_api/tests/test_distributor.py
chime_frb_api/tests/test_events.py
chime_frb_api/tests/test_metrics.py
chime_frb_api/tests/test_mimic.py
chime_frb_api/tests/test_parameters.py
chime_frb_api/tests/test_results.py
chime_frb_api/tests/test_sources.py
chime_frb_api/tests/test_stations.py
chime_frb_api/tests/test_swarm.py
chime_frb_api/tests/test_tns.py
chime_frb_api/tests/test_transfer_daemon.py
chime_frb_api/tests/test_voe.py
chime_frb_api/tests/test_voe_subscribers.py
chime_frb_api/tests/test_work.py
chime_frb_api/tests/test_work_http_operations.py
chime_frb_api/tests/test_workflow.py
chime_frb_api/workflow/__init__.py
chime_frb_api/workflow/daemons/__init__.py
chime_frb_api-2022.8.0.dist-info/LICENSE
chime_frb_api-2022.8.0.dist-info/WHEEL
chime_frb_api-2022.8.0.dist-info/METADATA
chime_frb_api-2022.8.0.dist-info/RECORD
