Metadata-Version: 2.1
Name: chime-frb-api
Version: 2022.8.0
Summary: CHIME/FRB API
Home-page: https://github.com/CHIMEFRB/frb-api
License: MIT
Author: Shiny Brar
Author-email: charanjotbrar@gmail.com
Requires-Python: >=3.6.2,<4.0.0
Classifier: Development Status :: 4 - Beta
Classifier: Intended Audience :: Developers
Classifier: Intended Audience :: Education
Classifier: Intended Audience :: Science/Research
Classifier: License :: OSI Approved :: MIT License
Classifier: Programming Language :: Python :: 3
Classifier: Programming Language :: Python :: 3.6
Classifier: Programming Language :: Python :: 3.7
Classifier: Programming Language :: Python :: 3.8
Classifier: Programming Language :: Python :: 3.9
Classifier: Topic :: Scientific/Engineering :: Astronomy
Classifier: Topic :: Software Development :: Libraries :: Python Modules
Provides-Extra: docs
Requires-Dist: attrs (>=21.2,<22.0)
Requires-Dist: mkdocs-material (>=8); extra == "docs"
Requires-Dist: mkdocstrings (>=0.16); extra == "docs"
Requires-Dist: pyjwt (>=2.4)
Requires-Dist: python-dateutil (>=2.8,<3.0)
Requires-Dist: pytkdocs[numpy-style] (>=0.10); extra == "docs"
Requires-Dist: requests (>=2.22,<3.0)
Project-URL: Documentation, https://github.com/CHIMEFRB/frb-api
Project-URL: Repository, https://github.com/CHIMEFRB/frb-api
